{
  "id": "1421",
  "name": "Modern Family",
  "originalName": "Modern Family",
  "overview": "The Pritchett-Dunphy-Tucker clan is a wonderfully large and blended family. They give us an honest and often hilarious look into the sometimes warm, sometimes twisted, embrace of the modern family.",
  "episodes": 201,
  "seasons": 9,
  "language": "en",
  "poster": "/gLAcu4VPCAb90oJvJ4nUJc5ZBQi.jpg",
  "backdrop": "/snxFgPvHMcpW5f8Q3wu6uRRycww.jpg",
  "firstAirDate": "2009-09-23",
  "lastAirDate": "2018-01-17",
  "rankings": {
    "imdb": null,
    "metacritic": 92,
    "tmdb": null
  },
  "score": 1.0108695652173914
}