{
  "id": "4344",
  "name": "Rescue Me",
  "originalName": "Rescue Me",
  "overview": "Rescue Me revolves around the lives of the men in a New York City firehouse, the crew of 62 Truck. Examining the fraternal nature and relationships of firefighters, the series tackles the daily drama of the life-and-death situations associated with being a firefighter, while exploring the ways the men use dark humor to protect their true emotions.",
  "episodes": 94,
  "seasons": 7,
  "language": "en",
  "poster": "/vcZG4uvfnd5RgO9H7OgVqHR3TbG.jpg",
  "backdrop": "/qHhBUi3xRngpIeImhyR2DIRAsqR.jpg",
  "firstAirDate": "2004-07-21",
  "lastAirDate": "2011-09-07",
  "rankings": {
    "imdb": null,
    "metacritic": 47,
    "tmdb": null
  },
  "score": 1.0212765957446808
}