{
  "id": "61068",
  "name": "Gomorrah",
  "originalName": "Gomorra - La serie",
  "overview": "Based on Robert Saviano's bestselling book, this gritty Italian crime drama paints a portrait of the brutal Neapolitan crime organisation the Camorra, as seen through the eyes of Ciro Di Marzo, the obedient and self- confident right-hand man of the clan's godfather, Pietro Savastano.",
  "episodes": 36,
  "seasons": 3,
  "language": "it",
  "poster": "/hbyns1rKCL1f9l0brzmwLHv6smL.jpg",
  "backdrop": "/szljytU8PkX9gMeMYmLp7H7zhVA.jpg",
  "firstAirDate": "2014-05-06",
  "lastAirDate": "2017-12-11",
  "rankings": {
    "imdb": null,
    "metacritic": null,
    "tmdb": 93
  },
  "score": 1.010752688172043
}