{
  "id": "64513",
  "name": "American Crime Story",
  "originalName": "American Crime Story",
  "overview": "An anthology series centered around some of history's most famous criminals.",
  "episodes": 19,
  "seasons": 2,
  "language": "en",
  "poster": "/oQa7cstZCCPCQ34xKY5rv548suI.jpg",
  "backdrop": "/j8NSaQJqnSOx8vsxwEukY3oATNj.jpg",
  "firstAirDate": "2016-02-02",
  "lastAirDate": "2018-03-21",
  "rankings": {
    "imdb": null,
    "metacritic": 51,
    "tmdb": null
  },
  "score": 1.0196078431372548
}
