{
  "id": "68837",
  "name": "Justice League Action",
  "originalName": "Justice League Action",
  "overview": "Batman, Superman and Wonder Woman will lead the DC Super Heroes against their most infamous foes.",
  "episodes": 52,
  "seasons": 1,
  "language": "en",
  "poster": "/tcS6G8lbmVU8uUtHhtlVpsxrYDm.jpg",
  "backdrop": "/8J4XFEhPFuJs7rfocpLo62f5Nhi.jpg",
  "firstAirDate": "2016-12-16",
  "lastAirDate": "2017-09-17",
  "rankings": {
    "imdb": 95,
    "metacritic": null,
    "tmdb": null
  },
  "score": 1.0105263157894737
}