{
  "id": "24188",
  "title": "Il Sorpasso",
  "backdrop": "/sNjjEyEX86INsiFCEzvLyGEWJSN.jpg",
  "language": "it",
  "originalTitle": "Il sorpasso",
  "overview": "Roberto, a shy law student in Rome, meets Bruno, a forty-year-old exuberant, capricious man, who takes him for a drive through the Roman and Tuscany countries in the summer. Along the way, they end up knowing each other and entering each other's lives. A twist at the end puts everything into perspective.",
  "poster": "/cnMOaDouZek6l7BcydVBrBlWegi.jpg",
  "releaseDate": "1962-12-04",
  "runtime": 105,
  "tagline": "",
  "rankings": {
    "bfi": null,
    "imdb": null,
    "letterboxd": null,
    "metacritic": null,
    "mubi": null,
    "rottenTomatoes": null,
    "tmdb": 69
  },
  "score": 1.0144927536231885
}