{
  "id": "432517",
  "title": "Sherlock: The Final Problem",
  "backdrop": "/3nXbWFPFGvjSE5bw8G6bBLVIzow.jpg",
  "language": "en",
  "originalTitle": "Sherlock: The Final Problem",
  "overview": "Long buried secrets finally come to light as someone has been playing a very long game indeed. Sherlock and John face their greatest ever challenge. Is the game finally over?",
  "poster": "/ySiqbi1sW7imVYbtECZS0xQ3Hmj.jpg",
  "releaseDate": "2017-01-15",
  "runtime": 90,
  "tagline": "",
  "rankings": {
    "bfi": null,
    "imdb": null,
    "letterboxd": null,
    "metacritic": null,
    "mubi": null,
    "rottenTomatoes": null,
    "tmdb": 37
  },
  "score": 1.027027027027027
}