{
  "id": "931",
  "title": "Don't Look Now",
  "backdrop": "/r8mKZ6RWpRR4uDPqc9HM7lR4A2m.jpg",
  "language": "en",
  "originalTitle": "Don't Look Now",
  "overview": "Laura and John, grieved by a terrible loss, meet in Venice, where John is in charge of the restoration of a church, two mysterious sisters, one of whom gives them a message sent from the afterlife.",
  "poster": "/mK1SxllUiyAjtugZg3M64e2CTu3.jpg",
  "releaseDate": "1973-12-03",
  "runtime": 110,
  "tagline": "Pass the warning.",
  "rankings": {
    "bfi": 103,
    "imdb": null,
    "letterboxd": null,
    "metacritic": null,
    "mubi": null,
    "rottenTomatoes": null,
    "tmdb": null
  },
  "score": 1.0097087378640777
}
